{"cameraMode":{"drawMode":24,"name":"Light Overlap","section":"Baked Global Illumination"},"sceneLighting":false,"audioPlay":false,"sceneViewState":{"m_AlwaysRefresh":false,"showFog":true,"showSkybox":true,"showFlares":true,"showImageEffects":true,"showParticleSystems":true,"showVisualEffectGraphs":true,"m_FxEnabled":false},"in2DMode":false,"pivot":{"x":-183.74395751953126,"y":35.4744758605957,"z":-20.617691040039064},"rotation":{"x":0.25618237257003786,"y":0.04830416664481163,"z":-0.012827555648982525,"w":0.9653546214103699},"size":91.10921478271485,"orthographic":true}